django_fixtures-0.4.dist-info/DESCRIPTION.rst
django_fixtures-0.4.dist-info/METADATA
django_fixtures-0.4.dist-info/RECORD
django_fixtures-0.4.dist-info/WHEEL
django_fixtures-0.4.dist-info/metadata.json
django_fixtures-0.4.dist-info/top_level.txt
fixtures/__init__.py
fixtures/util.py
fixtures/management/__init__.py
fixtures/management/commands/__init__.py
fixtures/management/commands/auto_features.py
fixtures/management/commands/auto_fixture.py
